Topsis/__init__.py
Topsis/__main__.py
Topsis_Avikal_102103131-0.0.1.dist-info/METADATA
Topsis_Avikal_102103131-0.0.1.dist-info/WHEEL
Topsis_Avikal_102103131-0.0.1.dist-info/entry_points.txt
Topsis_Avikal_102103131-0.0.1.dist-info/top_level.txt
Topsis_Avikal_102103131-0.0.1.dist-info/RECORD
