Metadata-Version: 2.1
Name: Topsis-Avikal-102103131
Version: 0.0.1
Author: Avikal Panwar
Author-email: avikalpanwar65@gmail.com
License: MIT
Classifier: License :: OSI Approved :: MIT License
Classifier: Programming Language :: Python :: 3.6
Classifier: Programming Language :: Python :: 3.7
Classifier: Programming Language :: Python :: 3.8
Requires-Dist: numpy
Requires-Dist: pandas
